mdtoc/__init__.py
mdtoc/__main__.py
mdtoc/main.py
mdtoc-1.3.data/scripts/mdtoc
mdtoc-1.3.dist-info/AUTHORS.md
mdtoc-1.3.dist-info/LICENSE
mdtoc-1.3.dist-info/METADATA
mdtoc-1.3.dist-info/WHEEL
mdtoc-1.3.dist-info/top_level.txt
mdtoc-1.3.dist-info/RECORD
